[
  {
    "id": "activity_1",
    "title":"Κατηγορίες Λέξεων",
    "description": "Βρείτε λέξεις για κάθε κατηγορία που σας ζητείται",
    "full_text": "",
    "video_url":"",
    "img_url":"words_categories.png",
    "instructions":["Κάντε click στο σύνδεσμο για να δείτε το έγγραφο"],
    "link": "https://drive.google.com/file/d/0B6htunInH8hvSzctQV90X0tXM2M/view?usp=sharing",
    "difficulty_level_id": "difficulty_level_1"
  },
  {
    "id": "activity_2",
    "title":"Απομνημόνευση λίστας λέξεων",
    "description": "O χρήστης πρέπει να απομνημονεύσει λέξεις και να δεί ποιά από αυτές έχει αλλάξει",
    "full_text": "",
    "video_url":"",
    "img_url":"",
    "instructions":["Κάντε click στο σύνδεσμο για να δείτε το έγγραφο", "Απομνημονεύστε τις λέξεις της πρώτης λίστας", "Στη συνέχεια καλύψτε τη λίστα αυτή."," Διαβάστε τη δεύτερη λίστα και βρείτε ποια από τις λέξεις έχει αλλάξει."],
    "link": "https://drive.google.com/file/d/0B2SImDUlGm_hWW1BUWNKdUI2bnFpZWl1SVN3a0lHQjRzOUZZ/view",
    "difficulty_level_id": "difficulty_level_1"
  },
  {
    "id": "activity_3",
    "title":"Θυμηθείτε τη λίστα για ψώνια",
    "description": "Προσπαθήστε να τα συγκρατήσετε στη μνήμη σας μια λίστα με αντικείμενα",
    "full_text": "",
    "video_url":"",
    "img_url":"",
    "instructions":["Κάντε click στο σύνδεσμο για να δείτε το έγγραφο", "Θέλετε να ψωνίσετε κάποια αντικείμενα από το σούπερ μάρκετ. Προσπαθήστε να τα συγκρατήσετε στη μνήμη σας", ". Γυρίστε το φύλλο και καταγράψτε όσα θυμάστε."],
    "link": "https://drive.google.com/file/d/0B6htunInH8hvMnNoTHNDQm1OMUE/view?usp=sharing",
    "difficulty_level_id": "difficulty_level_2"
  },
  {
    "id": "activity_4",
    "title":"Συμπλήρωση προτάσεων",
    "description": "Συμπληρώστε τις προτάσεις με τις κατάλληλες λέξεις, ώστε να έχουν νόημα.",
    "full_text": "",
    "video_url":"",
    "img_url":"",
    "instructions":["Κάντε click στο σύνδεσμο για να δείτε το έγγραφο"],
    "link": "https://drive.google.com/file/d/0B2SImDUlGm_hWW1BUWNKdUI2bnFpZWl1SVN3a0lHQjRzOUZZ/view",
    "difficulty_level_id": "difficulty_level_1"
  },
  {
    "id": "activity_5",
    "title":"Βρείτε τη λέξη",
    "description": "Διαβάστε τις τρεις λέξεις - κλειδιά και προσπαθήστε να βρείτε ποια λέξη περιγράφουν",
    "full_text": "",
    "video_url":"",
    "img_url":"",
    "instructions":["Κάντε click στο σύνδεσμο για να δείτε το έγγραφο"],
    "link": "https://drive.google.com/file/d/0B2SImDUlGm_hWW1BUWNKdUI2bnFpZWl1SVN3a0lHQjRzOUZZ/view",
    "difficulty_level_id": "difficulty_level_2"
  },
  {
    "id": "activity_6",
    "title":"Χρωματίζω και σκέφτομαι",
    "description": "Χρωματίστε τα σχήματα και ταυτόχρονα απαριθμήστε ότι σας ζητάται.",
    "full_text": "",
    "video_url":"",
    "img_url":"",
    "instructions":["Κάντε click στο σύνδεσμο για να δείτε το έγγραφο"],
    "link": "https://drive.google.com/file/d/0B2SImDUlGm_hWW1BUWNKdUI2bnFpZWl1SVN3a0lHQjRzOUZZ/view",
    "difficulty_level_id": "difficulty_level_2"
  },
  {
    "id": "activity_7",
    "title":"Σκίαση σχημάτων",
    "description": "Αντιγράψτε τα σχέδια, σκιάζοντας τα αντίστοιχα τετράγωνα.",
    "full_text": "",
    "video_url":"",
    "img_url":"",
    "instructions":["Κάντε click στο σύνδεσμο για να δείτε το έγγραφο"],
    "link": "https://drive.google.com/file/d/0B6htunInH8hvbGlQaXJEbW1rRW8/view?usp=sharing",
    "difficulty_level_id": "difficulty_level_1"
  },
  {
    "id": "activity_8",
    "title":"Αντιγράψτε σωστά",
    "description": "Προσπαθήστε να αντιγράψετε τους αριθμούς στις ίδιες θέσεις.",
    "full_text": "",
    "video_url":"",
    "img_url":"",
    "instructions":["Κάντε click στο σύνδεσμο για να δείτε το έγγραφο"],
    "link": "https://drive.google.com/file/d/0B2SImDUlGm_hWW1BUWNKdUI2bnFpZWl1SVN3a0lHQjRzOUZZ/view",
    "difficulty_level_id": "difficulty_level_1"
  },
  {
    "id": "activity_9",
    "title":"Σημασιολογικές κατηγορίες",
    "description": "Υπογραμμίστε ή κυκλώστε τις λέξεις που ανήκουν σε κατηγορίες",
    "full_text": "",
    "video_url":"",
    "img_url":"",
    "instructions":["Κάντε click στο σύνδεσμο για να δείτε το έγγραφο", "Υπογραμμίστε τις λέξεις που έχουν σχέση με τη μουσική", "Κυκλώστε τις λέξεις που αφορούν σε ζώα και ταυτόχρονα κυκλώστε τις λέξεις που αφορούν σε χρώματα"],
    "link": "https://drive.google.com/file/d/0B2SImDUlGm_hWW1BUWNKdUI2bnFpZWl1SVN3a0lHQjRzOUZZ/view",
    "difficulty_level_id": "difficulty_level_2"
  },
  {
    "id": "activity_10",
    "title":"Όνομα Ζώο Πράγμα Φυτό",
    "description": "Βρείτε μια λέξη σε κάθε κατηγορία, η οποία να ξεκινά από το γράμμα που σας δίνεται.",
    "full_text": "",
    "video_url":"",
    "img_url":"",
    "instructions":["Κάντε click στο σύνδεσμο για να δείτε το έγγραφο"],
    "link": "https://drive.google.com/file/d/0B6htunInH8hvT2tGTUxZMnN3cGM/view?usp=sharing",
    "difficulty_level_id": "difficulty_level_1"
  },
  {
    "id": "activity_11",
    "title":"Συνώνυμα - Αντίθετα",
    "description": "Βρείτε μια συνώνυμη και μια αντίθετη λέξη για καθεμία από τις λέξεις που σας δίνονται",
    "full_text": "",
    "video_url":"",
    "img_url":"",
    "instructions":["Κάντε click στο σύνδεσμο για να δείτε το έγγραφο"],
    "link": "https://drive.google.com/file/d/0B6htunInH8hvQ0t1a2NUNlBSajA/view?usp=sharing",
    "difficulty_level_id": "difficulty_level_1"
  }
]
